CHANGES.txt
LICENSE.txt
Makefile
README.txt
setup.cfg
setup.py
version.txt
raisin/__init__.py
raisin.restyler.egg-info/PKG-INFO
raisin.restyler.egg-info/SOURCES.txt
raisin.restyler.egg-info/dependency_links.txt
raisin.restyler.egg-info/entry_points.txt
raisin.restyler.egg-info/namespace_packages.txt
raisin.restyler.egg-info/not-zip-safe
raisin.restyler.egg-info/requires.txt
raisin.restyler.egg-info/top_level.txt
raisin/restyler/__init__.py
raisin/restyler/box.py
raisin/restyler/config.py
raisin/restyler/page.py
raisin/restyler/renderers.py
raisin/restyler/resource.py
raisin/restyler/templates/javascript.pt
raisin/restyler/tests/test_box.py
raisin/restyler/tests/test_page.py
raisin/restyler/tests/test_resource.py